pacup/__init__.py
pacup/__main__.py
pacup/parser.py
pacup/release_notes.py
pacup/utils.py
pacup/version.py
pacup-2.1.1.dist-info/LICENSE
pacup-2.1.1.dist-info/METADATA
pacup-2.1.1.dist-info/WHEEL
pacup-2.1.1.dist-info/entry_points.txt
pacup-2.1.1.dist-info/RECORD
