Metadata-Version: 2.1
Name: pacup
Version: 2.1.1
Summary: Help maintainers update pacscripts
Home-page: https://github.com/pacstall/pacup
License: GPL-3.0-or-later
Keywords: aur,cli,command line,console,debian,pacscript,pacstall,ubuntu,repology
Author: Sourajyoti Basak
Author-email: wiz28@protonmail.com
Requires-Python: >=3.10,<4
Classifier: Development Status :: 4 - Beta
Classifier: Environment :: Console
Classifier: Intended Audience :: Developers
Classifier: License :: OSI Approved :: GNU General Public License v3 or later (GPLv3+)
Classifier: Operating System :: POSIX :: Linux
Classifier: Programming Language :: Python :: 3
Classifier: Programming Language :: Python :: 3.10
Classifier: Programming Language :: Python :: 3.11
Classifier: Programming Language :: Python :: 3.12
Classifier: Programming Language :: Python :: 3 :: Only
Classifier: Programming Language :: Python :: 3.8
Classifier: Programming Language :: Python :: 3.9
Classifier: Programming Language :: Python :: Implementation :: CPython
Classifier: Topic :: System
Classifier: Topic :: Utilities
Classifier: Typing :: Typed
Requires-Dist: httpx (>=0.24,<0.25)
Requires-Dist: packaging (>=23,<23.3)
Requires-Dist: rich (>=13.0.0,<14.0.0)
Requires-Dist: typer (>=0.9.0,<0.10.0)
Project-URL: Documentation, https://github.com/pacstall/pacup/wiki
Project-URL: Repository, https://github.com/pacstall/pacup
